AhpAnpLib/__init__.py
AhpAnpLib/calcs_AHPLib copy.py
AhpAnpLib/calcs_AHPLib.py
AhpAnpLib/functions_AHPLib.py
AhpAnpLib/inputs_AHPLib.py
AhpAnpLib/ratings_AHPLib.py
AhpAnpLib/structs_AHPLib.py
AhpAnpLib-2.6.0.dist-info/LICENSE
AhpAnpLib-2.6.0.dist-info/METADATA
AhpAnpLib-2.6.0.dist-info/WHEEL
AhpAnpLib-2.6.0.dist-info/top_level.txt
AhpAnpLib-2.6.0.dist-info/RECORD
