Metadata-Version: 2.1
Name: AhpAnpLib
Version: 2.6.0
Summary: Analytic Hierarchy Process (AHP) and Analytic Network Process (ANP) Library
Author: Creative Decisions Foundation
License: MIT
License-File: LICENSE
Requires-Dist: graphviz <=0.20.1
Requires-Dist: matplotlib >=3.7.2
Requires-Dist: networkx >=3.1
Requires-Dist: numpy >=1.25.2
Requires-Dist: openpyxl >=3.1.2
Requires-Dist: pandas >=2.0.3
Requires-Dist: pydot >=1.4.2
Requires-Dist: Shapely >=2.0.1
Requires-Dist: tabulate >=0.9.0
Requires-Dist: XlsxWriter >=3.1.2
